cdcclimate
