Metadata-Version: 1.0
Name: cdcclimate
Version: 2.0.2
Summary: UNKNOWN
Home-page: UNKNOWN
Author: Clemens Drüe
Author-email: druee@uni-trier.de
License: EUPL-1.2
Platform: UNKNOWN
